optimum/tpu/__init__.py
optimum/tpu/cli.py
optimum/tpu/distributed_model.py
optimum/tpu/fsdp_v2.py
optimum/tpu/jetstream_pt_support.py
optimum/tpu/model.py
optimum/tpu/modeling.py
optimum/tpu/modeling_gemma.py
optimum/tpu/modeling_llama.py
optimum/tpu/modeling_mistral.py
optimum/tpu/static_cache_xla.py
optimum/tpu/version.py
optimum/tpu/xla_logger.py
optimum/tpu/xla_model_parallel.py
optimum/tpu/xla_mp_comm.py
optimum/tpu/generation/__init__.py
optimum/tpu/generation/logits_process.py
optimum/tpu/generation/token_selector.py
optimum_tpu-0.2.3.dist-info/LICENSE
optimum_tpu-0.2.3.dist-info/METADATA
optimum_tpu-0.2.3.dist-info/WHEEL
optimum_tpu-0.2.3.dist-info/entry_points.txt
optimum_tpu-0.2.3.dist-info/top_level.txt
optimum_tpu-0.2.3.dist-info/RECORD
