Metadata-Version: 2.1
Name: optimum-tpu
Version: 0.2.3
Summary: Optimum TPU is the interface between the Hugging Face Transformers library and Google Cloud TPU devices.
Author-email: "HuggingFace Inc. Machine Learning Optimization Team" <hardware@huggingface.co>
License:                                  Apache License
Project-URL: Homepage, https://hf.co/hardware
Project-URL: Documentation, https://hf.co/docs/optimum/tpu
Project-URL: Repository, https://github.com/huggingface/optimum-tpu
Project-URL: Issues, https://github.com/huggingface/optimum-tpu/issues
Keywords: transformers,fine-tuning,inference,tpu,cloud-tpu,gcp,google-cloud
Classifier: Development Status :: 2 - Pre-Alpha
Classifier: License :: OSI Approved :: Apache Software License
Classifier: Intended Audience :: Developers
Classifier: Intended Audience :: Education
Classifier: Intended Audience :: Science/Research
Classifier: Operating System :: OS Independent
Classifier: Programming Language :: Python :: 3.10
Classifier: Programming Language :: Python :: 3.11
Classifier: Topic :: Scientific/Engineering :: Artificial Intelligence
License-File: LICENSE
Requires-Dist: transformers==4.46.3
Requires-Dist: torch==2.5.1
Requires-Dist: torch-xla[tpu]==2.5.1
Requires-Dist: typer==0.6.1
Requires-Dist: loguru==0.6.0
Requires-Dist: sentencepiece==0.2.0
Provides-Extra: tests
Requires-Dist: pytest; extra == "tests"
Requires-Dist: safetensors; extra == "tests"
Provides-Extra: quality
Requires-Dist: black; extra == "quality"
Requires-Dist: ruff; extra == "quality"
Requires-Dist: isort; extra == "quality"
Provides-Extra: jetstream-pt
Requires-Dist: jetstream-pt; extra == "jetstream-pt"
Requires-Dist: torch-xla[pallas]==2.5.1; extra == "jetstream-pt"
